_bo4e_schemas_tool_version.py
bost/__init__.py
bost/__main__.py
bost/cache.py
bost/config.py
bost/logger.py
bost/operations.py
bost/pull.py
bost/py.typed
bost/schema.py
bo4e_schema_tool-0.0.9.dist-info/METADATA
bo4e_schema_tool-0.0.9.dist-info/WHEEL
bo4e_schema_tool-0.0.9.dist-info/entry_points.txt
bo4e_schema_tool-0.0.9.dist-info/RECORD
