Metadata-Version: 2.3
Name: BO4E-Schema-Tool
Version: 0.0.9
Summary: This little (python) tool allows to conveniently pull the BO4E-Schemas of a certain version and to edit them in certain ways.
Project-URL: Changelog, https://github.com/Hochfrequenz/BO4E-Schema-Tool/releases
Project-URL: Homepage, https://github.com/Hochfrequenz/BO4E-Schema-Tool
Author-email: Hochfrequenz Unternehmensberatung GmbH <info@hochfrequenz.de>
License: MIT
Keywords: bo4e,code-generator,schemas
Classifier: Development Status :: 4 - Beta
Classifier: Environment :: Console
Classifier: Intended Audience :: Developers
Classifier: License :: OSI Approved :: MIT License
Classifier: Operating System :: OS Independent
Classifier: Programming Language :: Python
Classifier: Programming Language :: Python :: 3 :: Only
Classifier: Programming Language :: Python :: 3.11
Classifier: Programming Language :: Python :: 3.12
Requires-Python: >=3.11
Requires-Dist: click
Requires-Dist: more-itertools
Requires-Dist: pydantic
Requires-Dist: pygithub
Requires-Dist: requests
